pvlink/__init__.py
pvlink/_frontend.py
pvlink/_version.py
pvlink/remoterenderer.py
pvlink/server.py
pvlink/simplerenderer.py
pvlink/utility.py
pvlink/static/extension.js
pvlink/static/index.js
pvlink/static/index.js.map
pvlink-0.3.1.data/data/etc/jupyter/nbconfig/notebook.d/pvlink.json
pvlink-0.3.1.data/data/share/jupyter/nbextensions/pvlink/extension.js
pvlink-0.3.1.data/data/share/jupyter/nbextensions/pvlink/index.js
pvlink-0.3.1.data/data/share/jupyter/nbextensions/pvlink/index.js.map
pvlink-0.3.1.dist-info/LICENSE.txt
pvlink-0.3.1.dist-info/METADATA
pvlink-0.3.1.dist-info/WHEEL
pvlink-0.3.1.dist-info/top_level.txt
pvlink-0.3.1.dist-info/RECORD
