Metadata-Version: 2.1
Name: pvlink
Version: 0.3.1
Summary: ParaView-Web RemoteRenderer in Jupyter
Home-page: https://gitlab.version.fz-juelich.de/jupyter4jsc/j4j_extras/pvlink
Author: Juelich Supercomputing Centre (JSC)
Author-email: a.grosch@fz-juelich.de
License: BSD
Keywords: ipython,jupyter,widgets,paraview,visualization
Platform: Linux
Platform: Mac OS X
Platform: Windows
Classifier: Development Status :: 4 - Beta
Classifier: Framework :: IPython
Classifier: Intended Audience :: Developers
Classifier: Intended Audience :: Science/Research
Classifier: Topic :: Multimedia :: Graphics
Classifier: Programming Language :: Python :: 2
Classifier: Programming Language :: Python :: 2.7
Classifier: Programming Language :: Python :: 3
Classifier: Programming Language :: Python :: 3.3
Classifier: Programming Language :: Python :: 3.4
Classifier: Programming Language :: Python :: 3.5
Classifier: Programming Language :: Python :: 3.6
Classifier: Programming Language :: Python :: 3.7
Requires-Dist: ipywidgets (>=7.0.0)
Requires-Dist: psutil (>=4.0.0)
Requires-Dist: twisted (>=19.2.1)
Requires-Dist: wslink (>=0.1.13)
